scembedding_jax/__init__.py
scembedding_jax/model.py
scembedding_jax-0.1.0.dist-info/licenses/LICENSE
scembedding_jax-0.1.0.dist-info/METADATA
scembedding_jax-0.1.0.dist-info/WHEEL
scembedding_jax-0.1.0.dist-info/top_level.txt
scembedding_jax-0.1.0.dist-info/RECORD
